{"snippets":[
  {"title":"Selection Sort Algorithm",
	"categories":"Programming, Java",
	"copyable":"true",
	"copyText":"Algorithm text here, or link to it",
	"favorite":"false",
	"linkToFull":"http://www.AddTheLinkHere.com",
	"imageUrl":"img/java-128.png",
	"imageAlt":"Code snippet"},

  {"title":"Insertion Sort Algorithm",
	"categories":"Programming, Java",
	"copyable":"true",
	"copyText":"Algorithm text here, or link to it",
	"favorite":"false",
	"linkToFull":"http://www.AddTheLinkHere.com",
	"imageUrl":"img/java-128.png",
	"imageAlt":"Code snippet"},

  {"title":"Merge Sort Algorithm",
	"categories":"Programming, Java",
	"copyable":"true",
	"copyText":"Algorithm text here, or link to it",
	"favorite":"false",
	"linkToFull":"http://www.AddTheLinkHere.com",
	"imageUrl":"img/java-128.png",
	"imageAlt":"Code snippet"},

  {"title":"Quick Sort Algorithm",
	"categories":"Programming, Java",
	"copyable":"true",
	"copyText":"Algorithm text here, or link to it",
	"favorite":"false",
	"linkToFull":"http://www.AddTheLinkHere.com",
	"imageUrl":"img/java-128.png",
	"imageAlt":"Code snippet"},

  {"title":"Load JSON File Locally",
	"categories":"Programming, JavaScript",
	"copyable":"true",
	"copyText":"_text_resources/load-json-file-locally.txt",
	"favorite":"false",
	"linkToFull":"http://codepen.io/KryptoniteDove/post/load-json-file-locally-using-pure-javascript",
	"imageUrl":"img/java-128.png",
	"imageAlt":"Code snippet"},

  {"title":"Keep Footer at Page Bottom",
      "categories":"Programming, CSS",
      "copyable":"true",
      "copyText":"_text_resources/keep-footer-at-page-bottom.txt",
      "favorite":"false",
      "linkToFull":"http://cssreset.com/how-to-keep-footer-at-bottom-of-page-with-css/",
      "imageUrl":"img/java-128.png",
      "imageAlt":"Code snippet"}
]}
